{
  "productosView": {
    "content": [
      {
        "id": 1,
        "nombre": "Notebook Lenovo",
        "precioCosto": 500,
        "precioVenta": 750,
        "stock": 10,
        "nombreProveedor": "Proveedor X",
        "nombreCategoria": "Electrónica",
        "nombreMarca": "Marca B"
      },
      {
        "id": 2,
        "nombre": "Mouse Logitech",
        "precioCosto": 10,
        "precioVenta": 20,
        "stock": 50,
        "nombreProveedor": "Proveedor X",
        "nombreCategoria": "Accesorios",
        "nombreMarca": "Marca B"
      },
      {
        "id": 3,
        "nombre": "Teclado Redragon",
        "precioCosto": 25,
        "precioVenta": 45,
        "stock": 20,
        "nombreProveedor": "Proveedor X",
        "nombreCategoria": "Accesorios",
        "nombreMarca": "Marca B"
      },
      {
        "id": 4,
        "nombre": "Monitor Samsung 24",
        "precioCosto": 85,
        "precioVenta": 120,
        "stock": 30,
        "nombreProveedor": "Proveedor X",
        "nombreCategoria": "Accesorios",
        "nombreMarca": "Marca B"
      },
      {
        "id": 5,
        "nombre": "Auriculares Sony",
        "precioCosto": 25,
        "precioVenta": 40,
        "stock": 25,
        "nombreProveedor": "Proveedor X",
        "nombreCategoria": "Accesorios",
        "nombreMarca": "Marca B"
      },
      {
        "id": 8,
        "nombre": "Disco SSD Kingston 480GB",
        "precioCosto": 25,
        "precioVenta": 35,
        "stock": 40,
        "nombreProveedor": "Proveedor X",
        "nombreCategoria": "Componentes",
        "nombreMarca": "Marca B"
      },
      {
        "id": 9,
        "nombre": "Memoria RAM Corsair 8GB",
        "precioCosto": 20,
        "precioVenta": 30,
        "stock": 35,
        "nombreProveedor": "Proveedor X",
        "nombreCategoria": "Componentes",
        "nombreMarca": "Marca B"
      },
      {
        "id": 13,
        "nombre": "Webcam Logitech HD",
        "precioCosto": 30,
        "precioVenta": 40,
        "stock": 15,
        "nombreProveedor": "Proveedor X",
        "nombreCategoria": "Accesorios",
        "nombreMarca": "Marca B"
      },
      {
        "id": 15,
        "nombre": "Parlantes Genius",
        "precioCosto": 20,
        "precioVenta": 30,
        "stock": 10,
        "nombreProveedor": "Proveedor X",
        "nombreCategoria": "Accesorios",
        "nombreMarca": "Marca B"
      }
    ],
    "totalElements": 15,
    "totalPages": 8,
    "number": 0
  },
  "productosRequest": {
    "content": [
      {
        "id": 1,
        "nombre": "Bici Montaña",
        "stock": 10,
        "precioCosto": 100,
        "precioVenta": 150,
        "proveedorid": 1,
        "categoriaid": 1,
        "marcaid": 1
      },
      {
        "id": 2,
        "nombre": "Casco",
        "stock": 2,
        "precioCosto": 20,
        "precioVenta": 40,
        "proveedorid": 1,
        "categoriaid": 2,
        "marcaid": 2
      }
    ],
    "totalElements": 4,
    "totalPages": 2,
    "number": 0
  },
  "ventas": {
    "content": [
      {
        "id": "V-001",
        "nombreCliente": "Juan Perez",
        "total": 190,
        "fechaVenta": "20-03-2026",
        "formaPago": "Efectivo",
        "observacion": "Cliente frecuente, descuento por compra múltiple",
        "Productos": [
          {
            "id": "2",
            "Nombre": "Mouse Logitech",
            "Cantidad": 2,
            "PrecioVenta": 20
          },
          {
            "id": "3",
            "Nombre": "Teclado Redragon",
            "Cantidad": 1,
            "PrecioVenta": 45
          },
          {
            "id": "15",
            "Nombre": "Parlantes Genius",
            "Cantidad": 3,
            "PrecioVenta": 30
          }
        ]
      },
      {
        "id": "V-002",
        "nombreCliente": "Maria Gomez",
        "total": 410,
        "fechaVenta": "21-03-2026",
        "formaPago": "Tarjeta",
        "observacion": "Pago realizado con tarjeta de crédito",
        "Productos": [
          {
            "id": "1",
            "Nombre": "Notebook Lenovo",
            "Cantidad": 1,
            "PrecioVenta": 750
          },
          {
            "id": "13",
            "Nombre": "Webcam Logitech HD",
            "Cantidad": 1,
            "PrecioVenta": 40
          }
        ]
      }
    ],
    "totalElements": 2,
    "totalPages": 1,
    "number": 0
  },
  "compra": {
    "content": [
      {
        "id": "C-001",
        "total": 520,
        "nombreProveedor": "TechSupplier",
        "fecha": "20-03-2026",
        "Productos": [
          {
            "id": "4",
            "Nombre": "Monitor Samsung 24\"",
            "Cantidad": 2,
            "Precio": 120
          },
          {
            "id": "8",
            "Nombre": "Disco SSD Kingston 480GB",
            "Cantidad": 4,
            "Precio": 35
          },
          {
            "id": "9",
            "Nombre": "Memoria RAM Corsair 8GB",
            "Cantidad": 2,
            "Precio": 30
          }
        ]
      },
      {
        "id": "C-002",
        "total": 400,
        "nombreProveedor": "AudioTech",
        "fecha": "21-03-2026",
        "Productos": [
          {
            "id": "5",
            "Nombre": "Auriculares Sony",
            "Cantidad": 5,
            "Precio": 40
          },
          {
            "id": "15",
            "Nombre": "Parlantes Genius",
            "Cantidad": 10,
            "Precio": 20
          }
        ]
      }
    ],
    "totalElements": 2,
    "totalPages": 1,
    "number": 0
  },
  "categoria": {
    "content": [
      {
        "id": 1,
        "nombre": "Bicicletas"
      },
      {
        "id": 2,
        "nombre": "Accesorios"
      },
      {
        "id": 3,
        "nombre": "Componentes"
      },
      {
        "id": 4,
        "nombre": "Herramientas"
      },
      {
        "id": 5,
        "nombre": "Muebles"
      },
      {
        "id": 6,
        "nombre": "Redes"
      },
      {
        "id": 7,
        "nombre": "Audio"
      },
      {
        "id": 8,
        "nombre": "Oficina"
      },
      {
        "id": 9,
        "nombre": "Electrónica"
      }
    ],
    "totalElements": 9,
    "totalPages": 3,
    "number": 0
  },
  "marca": {
    "content": [
      {
        "id": 1,
        "nombre": "Marca A"
      },
      {
        "id": 2,
        "nombre": "Marca B"
      },
      {
        "id": 3,
        "nombre": "Marca C"
      }
    ],
    "totalElements": 9,
    "totalPages": 3,
    "number": 0
  },
  "proveedor": {
    "content": [
      {
        "id": 1,
        "nombre": "Proveedor X"
      },
      {
        "id": 2,
        "nombre": "Proveedor Y"
      },
      {
        "id": 3,
        "nombre": "Proveedor Z"
      }
    ],
    "totalElements": 9,
    "totalPages": 3,
    "number": 0
  },
  "reparaciones": {
    "content": [
      {
        "id": 1,
        "nombreCliente": "Carlos Ramirez",
        "estado": "Aprobado_Presupuesto",
        "valorTotal": 15000,
        "valorManoDeObra": 5000,
        "fechaConfirmada": "20-03-2026",
        "detalles": [
          {
            "id": 1,
            "nombre": "Notebook Lenovo",
            "valorVenta": 10000,
            "cantidad": 1
          }
        ]
      },
      {
        "id": 2,
        "nombreCliente": "Ana Torres",
        "estado": "Finalizado",
        "valorTotal": 22000,
        "valorManoDeObra": 7000,
        "fechaConfirmada": "25-03-2026",
        "observacion": "Cambio de batería y limpieza general",
        "detalles": [
          {
            "id": 2,
            "nombre": "Mouse Logitech",
            "valorVenta": 12000,
            "cantidad": 1
          },
          {
            "id": 3,
            "nombre": "Teclado Redragon",
            "valorVenta": 3000,
            "cantidad": 1
          }
        ]
      }
    ],
    "totalElements": 1,
    "totalPages": 1,
    "number": 0
  },
  "balance": {
    "content": [
      {
        "ingresosSemestrales": 104600,
        "gastosSemestrales": 55400,
        "gananciasSemestrales": 49200,
        "promedioGananciasSemestrales": 17433
      }
    ]
  },
  "reparacionesMensuales": [
    {
      "mes": "Enero",
      "total": 15
    },
    {
      "mes": "Febrero",
      "total": 20
    },
    {
      "mes": "Marzo",
      "total": 18
    },
    {
      "mes": "Abril",
      "total": 25
    },
    {
      "mes": "Mayo",
      "total": 22
    },
    {
      "mes": "Junio",
      "total": 30
    }
  ],
  "pie": {
    "totalVentas": 45230,
    "totalReparaciones": 18500
  },
  "ventasMensuales": [
    {
      "mes": "Enero",
      "total": 14200
    },
    {
      "mes": "Febrero",
      "total": 16500
    },
    {
      "mes": "Marzo",
      "total": 18000
    },
    {
      "mes": "Abril",
      "total": 15800
    },
    {
      "mes": "Mayo",
      "total": 20100
    },
    {
      "mes": "Junio",
      "total": 20000
    }
  ],
  "comprasMensuales": [
    {
      "mes": "Enero",
      "total": 8000
    },
    {
      "mes": "Febrero",
      "total": 9500
    },
    {
      "mes": "Marzo",
      "total": 10200
    },
    {
      "mes": "Abril",
      "total": 8700
    },
    {
      "mes": "Mayo",
      "total": 9800
    },
    {
      "mes": "Junio",
      "total": 9200
    }
  ],
  "totalesActuales": {
    "ventas": 20000,
    "reparaciones": 4800
  }
}